{
    "47": "EPL",
    "41": "American Football",
    "54": "AutoMotoRacing",
    "17": "Athletics",
    "51": "Baseball",
    "34": "Bodybuilding/Fitness",
    "50": "Golf",
    "29": "Boxing",
    "19": "BrainGames",
    "36": "BreakDance",
    "23": "Cycling",
    "31": "Documentary",
    "1": "European Basketball",
    "37": "Extreme Sports",
    "9": "Fight Sports",
    "32": "Formula1",
    "45": "GAA (Gaelic)",
    "22": "Gymnastics",
    "59": "UFL",
    "39": "Handball",
    "2": "International Basket",
    "25": "IceHockey",
    "4": "International Soccer",
    "42": "KHL",
    "55": "MotoGP",
    "35": "KickBoxing/Muay Thai",
    "43": "La Liga",
    "15": "MotorSport",
    "24": "MLB",
    "28": "MMA",
    "11": "NBA",
    "3": "NCAA Basket/Football",
    "5": "NFL",
    "27": "NHL",
    "26": "Olympic games",
    "7": "Rugby",
    "44": "Serie A",
    "38": "Snooker/Pool",
    "30": "Streetball",
    "18": "Swimming/Aquatics",
    "56": "Ligue1",
    "46": "AFL(AustralianFB)",
    "12": "Tennis",
    "20": "Volleyball",
    "21": "Weightlifting",
    "16": "WinterSport",
    "33": "Wrestling/Grapling",
    "48": "Uncategorised",
    "60": "Champions League",
    "61": "Europa League",
    "63": "WNBA",
    "64": "NASCAR",
    "65": "FIBA 3x3 Basketball",
    "67": "Bundesliga",
    "68": "MLS",
    "69": "EuroLeague Basketbal",
    "70": "ELC",
    "71": "RhythmicGymnastics",
    "72": "BeachVolleyball",
    "73": "BeachSoccer",
    "74": "Chess",
    "75": "Bowling",
    "76": "BelgianProLeague",
    "77": "Bellator",
    "78": "Billard",
    "79": "Climbing",
    "80": "CrossFit",
    "81": "DutchEredivisie",
    "82": "IndyCar",
    "83": "GLeagueNBA",
    "84": "NCAABasketball",
    "85": "NCAAFootball",
    "86": "Sailing",
    "87": "Surfing",
    "88": "TableTennis",
    "89": "TourDeFrance",
    "90": "LaVuelta",
    "91": "Girod'Italia",
    "92": "UefaConferenceLeague",
    "93": "UEFAEuro",
    "94": "OlympicGamesParis24",
    "95": "WRCRally",
    "96": "CPL",
    "97": "CFL",
    "98": "PrimeiraPortugal",
    "53": "Cricket",
    "6": "European Soccer",
    "52": "Field Hockey",
    "58": "UFC",
    "57": "NRL"
  }
  